learning/PROJECTS/uvm/big-adder/model/verilog/peripheral_adder.sv
module peripheral_adder (
  // GLOBAL
  input clk,
  input rst,

  // CONTROL
  input      in_valid,
  output reg out_valid,

  // DATA
  input      [7:0] in1,
  input      [7:0] in2,

  output reg [8:0] data_out
);

  //////////////////////////////////////////////////////////////////////////////
  // Types
  //////////////////////////////////////////////////////////////////////////////

  parameter STARTER_STATE = 1'b0;
  parameter ENDER_STATE = 1'b1;

  //////////////////////////////////////////////////////////////////////////////
  // Constants
  //////////////////////////////////////////////////////////////////////////////

  parameter ZERO_DATA = 0;

  //////////////////////////////////////////////////////////////////////////////
  // Signals
  //////////////////////////////////////////////////////////////////////////////

  // Finite State Machine
  reg  adder_ctrl_fsm_int;

  //////////////////////////////////////////////////////////////////////////////
  // Body
  //////////////////////////////////////////////////////////////////////////////

  // CONTROL
  always @(posedge clk or posedge rst) begin
    if (rst == 1'b1) begin
      // Data Outputs
      data_out           <= ZERO_DATA;

      // Control Outputs
      out_valid          <= 1'b0;

      // FSM Control
      adder_ctrl_fsm_int <= STARTER_STATE;

    end else begin
      case (adder_ctrl_fsm_int)
        STARTER_STATE: begin  // STEP 0
          // Control Outputs
          out_valid <= 1'b0;

          if (in_valid == 1'b1) begin
            // FSM Control
            adder_ctrl_fsm_int <= ENDER_STATE;
          end
        end
        ENDER_STATE: begin  // STEP 1

          // Data Outputs
          data_out           <= in1 + in2;

          // Control Outputs
          out_valid          <= 1'b1;

          // FSM Control
          adder_ctrl_fsm_int <= STARTER_STATE;
        end
        default: begin
          // FSM Control
          adder_ctrl_fsm_int <= STARTER_STATE;
        end
      endcase
    end
  end

endmodule

learning/PROJECTS/uvm/big-adder/validation/tests/peripheral_testbench.sv
module peripheral_testbench;
  // Clock and Reset declaration
  reg        clk;
  reg        rst;

  // Data Signals
  reg        in_valid;
  wire       out_valid;

  // Data Signals
  reg  [7:0] in1;
  reg  [7:0] in2;

  wire [8:0] data_out;

  // DUT instantiation
  peripheral_adder  #(
    .DATA_SIZE(8)
  ) dut (
    .clk(clk),
    .rst(rst),

    .in_valid(in_valid),
    .out_valid(out_valid),

    .in1(in1),
    .in2(in2),

    .data_out(data_out)
  );

  // Clock Generation
  always #1 clk = ~clk;

  initial begin
    clk = 0;
  end

  // Reset Generation
  initial begin
    rst = 0;
    #3;

    rst = 1;
    #2;

    rst = 0;
    #4;
  end

  // Start Generation
  initial begin
    in_valid = 0;
    #7;

    repeat (10) begin
      in_valid = 1;
      #2;

      in_valid = 0;
      #10;
    end
  end

  initial begin
    // Dump waves
    $dumpfile("system.vcd");
    $dumpvars(0, peripheral_testbench);

    in1 = 0;
    in2 = 0;
    #7;

    repeat (10) begin
      in1 = $urandom();
      in2 = $urandom();
      #12;
    end

    $display("End");
    $finish();
  end
endmodule

learning/PROJECTS/uvm/big-adder/sim/verilog/validation/tests/iverilog/system.vcd
$date
	Thu Jan 18 11:17:02 2024
$end
$version
	Icarus Verilog
$end
$timescale
	1s
$end
$scope module peripheral_testbench $end
$var wire 1 ! out_valid $end
$var wire 9 " data_out [8:0] $end
$var reg 1 # clk $end
$var reg 8 $ in1 [7:0] $end
$var reg 8 % in2 [7:0] $end
$var reg 1 & in_valid $end
$var reg 1 ' rst $end
$scope module dut $end
$var wire 1 # clk $end
$var wire 8 ( in1 [7:0] $end
$var wire 8 ) in2 [7:0] $end
$var wire 1 & in_valid $end
$var wire 1 ' rst $end
$var reg 1 * adder_ctrl_fsm_int $end
$var reg 9 + data_out [8:0] $end
$var reg 1 ! out_valid $end
$upscope $end
$upscope $end
$enddefinitions $end
#0
$dumpvars
bx +
x*
b0 )
b0 (
0'
0&
b0 %
b0 $
0#
bx "
x!
$end
#1
0*
1#
#2
0#
#3
0!
b0 "
b0 +
1#
1'
#4
0#
#5
1#
0'
#6
0#
#7
1*
1#
b10000001 %
b10000001 )
b100100 $
b100100 (
1&
#8
0#
#9
0*
1!
b10100101 "
b10100101 +
1#
0&
#10
0#
#11
0!
1#
#12
0#
#13
1#
#14
0#
#15
1#
#16
0#
#17
1#
#18
0#
#19
1*
1#
1&
b1100011 %
b1100011 )
b1001 $
b1001 (
#20
0#
#21
0*
1!
b1101100 "
b1101100 +
1#
0&
#22
0#
#23
0!
1#
#24
0#
#25
1#
#26
0#
#27
1#
#28
0#
#29
1#
#30
0#
#31
1*
1#
1&
b10001101 %
b10001101 )
b1101 $
b1101 (
#32
0#
#33
0*
1!
b10011010 "
b10011010 +
1#
0&
#34
0#
#35
0!
1#
#36
0#
#37
1#
#38
0#
#39
1#
#40
0#
#41
1#
#42
0#
#43
1*
1#
1&
b10010 %
b10010 )
b1100101 $
b1100101 (
#44
0#
#45
0*
1!
b1110111 "
b1110111 +
1#
0&
#46
0#
#47
0!
1#
#48
0#
#49
1#
#50
0#
#51
1#
#52
0#
#53
1#
#54
0#
#55
1*
1#
1&
b1101 %
b1101 )
b1 $
b1 (
#56
0#
#57
0*
1!
b1110 "
b1110 +
1#
0&
#58
0#
#59
0!
1#
#60
0#
#61
1#
#62
0#
#63
1#
#64
0#
#65
1#
#66
0#
#67
1*
1#
1&
b111101 %
b111101 )
b1110110 $
b1110110 (
#68
0#
#69
0*
1!
b10110011 "
b10110011 +
1#
0&
#70
0#
#71
0!
1#
#72
0#
#73
1#
#74
0#
#75
1#
#76
0#
#77
1#
#78
0#
#79
1*
1#
1&
b10001100 %
b10001100 )
b11101101 $
b11101101 (
#80
0#
#81
0*
1!
b101111001 "
b101111001 +
1#
0&
#82
0#
#83
0!
1#
#84
0#
#85
1#
#86
0#
#87
1#
#88
0#
#89
1#
#90
0#
#91
1*
1#
1&
b11000110 %
b11000110 )
b11111001 $
b11111001 (
#92
0#
#93
0*
1!
b110111111 "
b110111111 +
1#
0&
#94
0#
#95
0!
1#
#96
0#
#97
1#
#98
0#
#99
1#
#100
0#
#101
1#
#102
0#
#103
1*
1#
1&
b10101010 %
b10101010 )
b11000101 $
b11000101 (
#104
0#
#105
0*
1!
b101101111 "
b101101111 +
1#
0&
#106
0#
#107
0!
1#
#108
0#
#109
1#
#110
0#
#111
1#
#112
0#
#113
1#
#114
0#
#115
1*
1#
1&
b1110111 %
b1110111 )
b11100101 $
b11100101 (
#116
0#
#117
0*
1!
b101011100 "
b101011100 +
1#
0&
#118
0#
#119
0!
1#
