learning/PROJECTS/uvm/small-adder/rtl/verilog/ntm_design.sv
module ntm_design (
  // GLOBAL
  input wire clk,
  input wire rst,

  // CONTROL
  input      in_valid,
  output reg out_valid,

  // DATA
  input [7:0] in1,
  input [7:0] in2,

  output reg [15:0] data_out
);

  //////////////////////////////////////////////////////////////////////////////
  // Types
  //////////////////////////////////////////////////////////////////////////////

  parameter STARTER_STATE = 1'b0;
  parameter ENDER_STATE = 1'b1;

  //////////////////////////////////////////////////////////////////////////////
  // Constants
  //////////////////////////////////////////////////////////////////////////////

  parameter ZERO_SDATA = 0;
  parameter ONE_SDATA  = 1;

  //////////////////////////////////////////////////////////////////////////////
  // Signals
  //////////////////////////////////////////////////////////////////////////////

  // Finite State Machine
  reg multiplier_ctrl_fsm_int;

  // Data Internal
  logic [15:0] multiplier_int;

  // Control Internal
  logic [7:0] index_loop;

  always @(posedge clk or posedge rst) begin
    if (rst) begin
      // Data Outputs
      data_out <= ZERO_SDATA;

      // Control Outputs
      out_valid <= 1'b0;

      // Data Internal
      multiplier_int <= ZERO_SDATA;

      // Control Internal
      index_loop <= ZERO_SDATA;
    end else begin
      case (multiplier_ctrl_fsm_int)
        STARTER_STATE: begin  // STEP 0
          // Control Outputs
          out_valid <= 1'b0;

          if (in_valid) begin
            // Data Internal
            multiplier_int <= ZERO_SDATA;

            // Control Internal
            index_loop <= ZERO_SDATA;

            // FSM Control
            multiplier_ctrl_fsm_int <= ENDER_STATE;
          end
        end
        ENDER_STATE: begin  // STEP 1
          if (in2[7]) begin
            if (index_loop == in2) begin
              // Data Outputs
              data_out <= multiplier_int;

              // Control Outputs
              out_valid <= 1'b1;

              // FSM Control
              multiplier_ctrl_fsm_int <= STARTER_STATE;
            end else begin
              // Data Internal
              multiplier_int <= multiplier_int - ({8'h00, in1});

              // Control Internal
              index_loop <= index_loop - ONE_SDATA;
            end
          end else begin
            if (index_loop == in2) begin
              // Data Outputs
              data_out <= multiplier_int;

              // Control Outputs
              out_valid <= 1'b1;

              // FSM Control
              multiplier_ctrl_fsm_int <= STARTER_STATE;
            end else begin
              // Data Internal
              multiplier_int <= multiplier_int + ({8'h00, in1});

              // Control Internal
              index_loop <= index_loop + ONE_SDATA;
            end
          end
        end
        default: begin
          // FSM Control
          multiplier_ctrl_fsm_int <= STARTER_STATE;
        end
      endcase
    end
  end

endmodule

learning/PROJECTS/uvm/small-adder/verification/application/ntm_testbench.sv
////////////////////////////////////////////////////////////////////////////////
//                                            __ _      _     _               //
//                                           / _(_)    | |   | |              //
//                __ _ _   _  ___  ___ _ __ | |_ _  ___| | __| |              //
//               / _` | | | |/ _ \/ _ \ '_ \|  _| |/ _ \ |/ _` |              //
//              | (_| | |_| |  __/  __/ | | | | | |  __/ | (_| |              //
//               \__, |\__,_|\___|\___|_| |_|_| |_|\___|_|\__,_|              //
//                  | |                                                       //
//                  |_|                                                       //
//                                                                            //
//                                                                            //
//              Peripheral-NTM for MPSoC                                      //
//              Neural Turing Machine for MPSoC                               //
//                                                                            //
////////////////////////////////////////////////////////////////////////////////
// Copyright (c) 2022-2025 by the author(s)
//
// Permission is hereby granted, free of charge, to any person obtaining a copy
// of this software and associated documentation files (the "Software"), to deal
// in the Software without restriction, including without limitation the rights
// to use, copy, modify, merge, publish, distribute, sublicense, and/or sell
// copies of the Software, and to permit persons to whom the Software is
// furnished to do so, subject to the following conditions:
//
// The above copyright notice and this permission notice shall be included in
// all copies or substantial portions of the Software.
//
// THE SOFTWARE IS PROVIDED "AS IS", WITHOUT WARRANTY OF ANY KIND, EXPRESS OR
// IMPLIED, INCLUDING BUT NOT LIMITED TO THE WARRANTIES OF MERCHANTABILITY,
// FITNESS FOR A PARTICULAR PURPOSE AND NONINFRINGEMENT. IN NO EVENT SHALL THE
// AUTHORS OR COPYRIGHT HOLDERS BE LIABLE FOR ANY CLAIM, DAMAGES OR OTHER
// LIABILITY, WHETHER IN AN ACTION OF CONTRACT, TORT OR OTHERWISE, ARISING FROM,
// OUT OF OR IN CONNECTION WITH THE SOFTWARE OR THE USE OR OTHER DEALINGS IN
// THE SOFTWARE.
//
////////////////////////////////////////////////////////////////////////////////
// Author(s):
//   Paco Reina Campo <pacoreinacampo@queenfield.tech>

module ntm_testbench;
  // Clock and Reset declaration
  reg        clk;
  reg        rst;

  // Data Signals
  reg        in_valid;
  wire       out_valid;

  // Data Signals
  reg  [7:0] ip1;
  reg  [7:0] ip2;

  wire [15:0] data_out;

  // DUT instantiation
  ntm_design dut (
    .clk(clk),
    .rst(rst),

    .in_valid(in_valid),
    .in1(ip1),
    .in2(ip2),

    .out_valid(out_valid),
    .data_out(data_out)
  );

  // Clock Generation
  always #1 clk = ~clk;

  initial begin
    // Dump waves
    $dumpfile("system.vcd");
    $dumpvars(0, ntm_testbench);

    clk = 0;
    rst = 0;

    in_valid = 0;

    ip1 = 0;
    ip2 = 0;
    #2;

    rst = 1;
    #2;

    rst = 0;
    #4;

    in_valid = 1;
    ip1 = 5;
    ip2 = 2;
    #2;

    in_valid = 0;
    #10;

    $display("End");
    $finish();
  end
endmodule

learning/PROJECTS/uvm/small-adder/sim/verilog/verification/tests/iverilog/system.vcd
$date
	Thu Jan 18 21:59:59 2024
$end
$version
	Icarus Verilog
$end
$timescale
	1s
$end
$scope module ntm_testbench $end
$var wire 1 ! out_valid $end
$var wire 16 " data_out [15:0] $end
$var reg 1 # clk $end
$var reg 1 $ in_valid $end
$var reg 8 % ip1 [7:0] $end
$var reg 8 & ip2 [7:0] $end
$var reg 1 ' rst $end
$scope module dut $end
$var wire 1 # clk $end
$var wire 8 ( in1 [7:0] $end
$var wire 8 ) in2 [7:0] $end
$var wire 1 $ in_valid $end
$var wire 1 ' rst $end
$var reg 16 * data_out [15:0] $end
$var reg 8 + index_loop [7:0] $end
$var reg 1 , multiplier_ctrl_fsm_int $end
$var reg 16 - multiplier_int [15:0] $end
$var reg 1 ! out_valid $end
$upscope $end
$upscope $end
$enddefinitions $end
#0
$dumpvars
bx -
x,
bx +
bx *
b0 )
b0 (
0'
b0 &
b0 %
0$
0#
bx "
x!
$end
#1
0,
1#
#2
b0 +
b0 -
0!
b0 "
b0 *
0#
1'
#3
1#
#4
0#
0'
#5
1#
#6
0#
#7
1#
#8
0#
b10 &
b10 )
b101 %
b101 (
1$
#9
1,
1#
#10
0#
0$
#11
b1 +
b101 -
1#
#12
0#
#13
b10 +
b1010 -
1#
#14
0#
#15
0,
1!
b1010 "
b1010 *
1#
#16
0#
#17
0!
1#
